pontypg/__init__.py
pontypg/errortrap.py
pontypg/fetch.py
pontypg/provider.py
pontypg/py.typed
pontypg-0.2.4.dist-info/METADATA
pontypg-0.2.4.dist-info/WHEEL
pontypg-0.2.4.dist-info/top_level.txt
pontypg-0.2.4.dist-info/RECORD
