Metadata-Version: 2.1
Name: pontypg
Version: 0.2.4
Summary: Basic async postgres utils. Extends ponty.
Home-page: https://github.com/csira/pontypg
License: BSD
Classifier: Development Status :: 4 - Beta
Classifier: Environment :: Web Environment
Classifier: Framework :: AsyncIO
Classifier: Intended Audience :: Developers
Classifier: License :: Freely Distributable
Classifier: License :: OSI Approved :: BSD License
Classifier: Operating System :: OS Independent
Classifier: Programming Language :: Python
Classifier: Programming Language :: Python :: 3
Classifier: Programming Language :: Python :: 3.8
Classifier: Programming Language :: Python :: 3.9
Classifier: Programming Language :: Python :: 3.10
Classifier: Topic :: Database
Classifier: Topic :: Software Development :: Libraries :: Python Modules
Classifier: Typing :: Typed
Requires-Python: >=3.8
Requires-Dist: asyncpg (>=0.21.0)
Requires-Dist: ponty (>=0.2.2)
Requires-Dist: typing-extensions (==4.2.0)
